src/Instr_Mem.sv
module Instr_Mem #(parameter N = 32)
(
    input logic reset, clk,
    input logic [N-1:0] address,
    output logic [N-1:0] instruction_out
);
logic [N-1:0] instruction_mem [1023:0];

always @(posedge clk) begin
    instruction_out <= (reset) ? 0 : instruction_mem[address[11:2]];
end

endmodule

tb/Instr_Mem_tb.sv
module Instr_Mem_tb;
    localparam N = 32;
    logic reset, clk;
    logic [N-1:0] address, instruction_out;

    Instr_Mem dut(
        .clk(clk),
        .reset(reset),
        .address(address),
        .instruction_out(instruction_out)
    );

    integer i;

    task check(input logic [31:0] addr_to_test, input logic expect_reset);
        begin
            address = addr_to_test;
            @(posedge clk); #1;

            if (expect_reset) begin
                if (instruction_out === 32'b0)
                    $display("[PASSED] Reset Test | Addr: %h", addr_to_test, instruction_out);
            end else begin
                if (instruction_out === (addr_to_test[11:2] * 10))
                    $display("[PASSED] Read Test  | Addr: %h | Data: %d", addr_to_test, instruction_out);
                else
                    $display("[FAILED] Read Test  | Addr: %h | Expected: %d | Got: %h", 
                             addr_to_test, (addr_to_test[11:2]*10), instruction_out);
            end
        end
    endtask

    initial begin
        $dumpfile("Instr_Mem.vcd");
        $dumpvars(0, Instr_Mem_tb);

        $monitor("Time: %0t | Reset: %b | Addr: %h | Instr: %d", $time, reset, address, instruction_out);

        for (i = 0; i < 1024; i = i + 1) begin
            dut.ROM[i] = i * 10;
        end

        reset = 1; clk = 0; address = 32'b00000000;
        
        check(32'h0000_0000, 1);
        check(32'h0000_03FC, 1);

        repeat(2) @(posedge clk); reset = 0;
        check(32'h0000_0000, 0);
        check(32'h0000_03FC, 0);
       
        check(32'h0000_0004, 0);
        check(32'h0000_0005, 0);
        check(32'h0000_0007, 0);
        
        reset = 1;
        check(32'h0000_0010, 1);
        reset = 0;
        check(32'h0000_0010, 0); 

        $finish;
    end

    always #5 clk = ~clk;

endmodule

waveforms/Instr_Mem.vcd
$date
	Thu Feb 26 15:12:55 2026
$end
$version
	Icarus Verilog
$end
$timescale
	1s
$end
$scope module Instr_Mem_tb $end
$var wire 32 ! instruction_out [31:0] $end
$var parameter 32 " N $end
$var reg 32 # address [31:0] $end
$var reg 1 $ clk $end
$var reg 1 % reset $end
$var integer 32 & i [31:0] $end
$scope module dut $end
$var wire 32 ' address [31:0] $end
$var wire 1 $ clk $end
$var wire 1 % reset $end
$var parameter 32 ( N $end
$var reg 32 ) instruction_out [31:0] $end
$upscope $end
$scope task check $end
$var reg 32 * addr_to_test [31:0] $end
$var reg 1 + expect_reset $end
$upscope $end
$upscope $end
$enddefinitions $end
$comment Show the parameter values. $end
$dumpall
b100000 (
b100000 "
$end
#0
$dumpvars
1+
b0 *
b0 )
b0 '
b10000000000 &
1%
0$
b0 #
b0 !
$end
#5
1$
#6
b1111111100 #
b1111111100 '
b1111111100 *
#10
0$
#15
1$
#20
0$
#25
1$
#30
0$
#35
b0 #
b0 '
0+
b0 *
0%
1$
#40
0$
#45
1$
#46
b1111111100 #
b1111111100 '
b1111111100 *
#50
b100111110110 !
b100111110110 )
0$
#55
1$
#56
b100 #
b100 '
b100 *
#60
b1010 !
b1010 )
0$
#65
1$
#66
b101 #
b101 '
b101 *
#70
0$
#75
1$
#76
b111 #
b111 '
b111 *
#80
0$
#85
1$
#86
b10000 #
b10000 '
1+
b10000 *
1%
#90
b0 !
b0 )
0$
#95
1$
#96
0+
0%
#100
b101000 !
b101000 )
0$
